securecodechecker/__init__.py
securecodechecker/checker.py
securecodechecker-0.1.0.dist-info/LICENSE
securecodechecker-0.1.0.dist-info/METADATA
securecodechecker-0.1.0.dist-info/WHEEL
securecodechecker-0.1.0.dist-info/top_level.txt
securecodechecker-0.1.0.dist-info/RECORD
