Metadata-Version: 2.2
Name: securecodechecker
Version: 0.1.0
Summary: A Python module to scan code for common insecure coding patterns (for ethical and educational use).
Home-page: https://github.com/yourusername/securecodechecker
Author: raayan
Author-email: your.email@example.com
Classifier: Programming Language :: Python :: 3
Classifier: License :: OSI Approved :: MIT License
Classifier: Operating System :: OS Independent
Requires-Python: >=3.6
License-File: LICENSE
Dynamic: author
Dynamic: author-email
Dynamic: classifier
Dynamic: description
Dynamic: description-content-type
Dynamic: home-page
Dynamic: requires-python
Dynamic: summary
